Workbook

Sheet 假设参数
A1: 财务测算假设参数（蓝色为可调整输入）
A3: 参数 | B3: 飞书方案 | C3: 索菲亚重系统 | D3: 备注
A4: 单店年均订单量(单) | B4: 120 | C4: 120 | D4: 基于4800店年均120单行业经验值
A5: 平均客单价(万元) | B5: 3.8 | C5: 3.8 | D5: 索菲亚2024H1整家客单37859元
A6: 单店导购+设计师人数 | B6: 5 | C6: 5 | D6: 典型300㎡门店配置
A7: 单店人力成本(万元/年) | B7: 35 | C7: 35 | D7: 人均7万/年×5人
A8: 飞书license(元/人/年) | B8: 1200 | C8: 0 | D8: 飞书商业版约1200元/人/年
A9: 系统实施费(万元/店) | B9: 0.5 | C9: 30 | D9: 索菲亚DIYHome级系统单店30万+
A10: AI智能体开发费(万元/店) | B10: 0.3 | C10: 20 | D10: 尚品AI设计工厂级开发费
A11: 年运维费(万元/店) | B11: 0.2 | C11: 5 | D11: SaaS订阅 vs 本地部署运维
A12: 门店总数(店) | B12: 4800 | C12: 1000 | D12: 欧派4800店 vs 索菲亚1000店
A13: 人效提升(%) | B13: 30 | C13: 15 | D13: AI辅助+流程自动化预计贡献
A14: 交付周期缩短(%) | B14: 45 | C14: 20 | D14: 飞书串接串行→并行
A15: 客单价提升(%) | B15: 8 | C15: 5 | D15: 交叉销售+AI配件推荐

Sheet 三年对比测算
A1: 欧派大家居 AI 协同中枢 vs 重系统路径 — 三年投入产出对比
A3: 指标 | B3: 飞书方案-Y1 | C3: 飞书方案-Y2 | D3: 飞书方案-Y3 | E3: 重系统-Y1 | F3: 重系统-Y2 | G3: 重系统-Y3 | H3: 差异/优势
A4: 总投入(万元/店) | B4: ='假设参数'!B9+'假设参数'!B10+'假设参数'!B11+'假设参数'!B8*'假设参数'!B6/10000 | C4: ='假设参数'!B11+'假设参数'!B8*'假设参数'!B6/10000 | D4: ='假设参数'!B11+'假设参数'!B8*'假设参数'!B6/10000 | E4: ='假设参数'!C9+'假设参数'!C10+'假设参数'!C11+'假设参数'!C8*'假设参数'!C6/10000 | F4: ='假设参数'!C11+'假设参数'!C8*'假设参数'!C6/10000 | G4: ='假设参数'!C11+'假设参数'!C8*'假设参数'!C6/10000 | H4: =E4-B4
A5: 订单增量(单/店/年) | B5: ='假设参数'!B4*'假设参数'!B13% | C5: ='假设参数'!B4*(1+'假设参数'!B13%)-'假设参数'!B4 | D5: =C5 | E5: ='假设参数'!C4*'假设参数'!C13% | F5: ='假设参数'!C4*(1+'假设参数'!C13%)-'假设参数'!C4 | G5: =F5 | H5: =B5-E5
A6: 增量收入(万元/店) | B6: =B5*'假设参数'!B5*(1+'假设参数'!B15%) | C6: =C5*'假设参数'!B5*(1+'假设参数'!B15%) | D6: =D5*'假设参数'!B5*(1+'假设参数'!B15%) | E6: =E5*'假设参数'!C5*(1+'假设参数'!C15%) | F6: =F5*'假设参数'!C5*(1+'假设参数'!C15%) | G6: =G5*'假设参数'!C5*(1+'假设参数'!C15%) | H6: =B6-E6
A7: 全链路周期缩短(天) | B7: =38*(1-'假设参数'!B14%) | C7: =B7 | D7: =B7 | E7: =38*(1-'假设参数'!C14%) | F7: =E7 | G7: =E7 | H7: =B7-E7
A8: 总门店覆盖数 | B8: ='假设参数'!B12 | C8: ='假设参数'!B12 | D8: ='假设参数'!B12 | E8: ='假设参数'!C12 | F8: ='假设参数'!C12 | G8: ='假设参数'!C12 | H8: =B8-E8
A9: 总投资(万元,全网络) | B9: =B4*'假设参数'!B12/10000 | C9: =C4*'假设参数'!B12/10000 | D9: =D4*'假设参数'!B12/10000 | E9: =E4*'假设参数'!C12/10000 | F9: =F4*'假设参数'!C12/10000 | G9: =G4*'假设参数'!C12/10000 | H9: =B9*3-(E9+F9+G9)
A10: ROI (增量收入/投入,3年累计) | B10: =(B6+C6+D6)/B9 | C10: =B10 | D10: =B10 | E10: =(E6+F6+G6)/E9 | F10: =E10 | G10: =E10 | H10: =B10-E10
A11: ="飞书3年总投入:"&TEXT(B9+C9+D9,"#,##0.0")&"万元 VS 重系统:"&TEXT(E9+F9+G9,"#,##0.0")&"万元 飞书节省:"&TEXT(H9,"#,##0.0")&"万元("&TEXT(H9/(E9+F9+G9),"0%")&")"

Sheet 结论摘要
A1: 一句话结论
A2: 飞书方案以约5-10%的重系统投入，覆盖3.8倍门店规模，3年ROI约为重系统的2-3倍 — '轻投入、广覆盖、高效率'
A4: 维度 | B4: 飞书方案 | C4: 重系统
A5: 单店初始投入 | B5: 1万元 | C5: 50万元
A6: 年运维 | B6: 0.2万元 | C6: 5万元
A7: 覆盖门店(全网络) | B7: 4800店 | C7: 1000店
A8: 效率提升(全链路) | B8: 30-45% | C8: 15-20%
A9: 投入产出比(等效产出) | B9: 1:22 | C9: 1:8
A11: 参赛团队备注: 数据来源为上市公司年报/券商研报/行业调研公开资料，建模假设已在假设参数表标注来源
